{
  "users": [
    {
      "id": 1,
      "email": "username@gmail.com",
      "created_at": "1668990427",
      "updated_at": "1671582429",
      "notes": [
        {
          "id": 1,
          "user_id": 1,
          "note_body": "Lorem ipsum, dolor sit amet consectetur adipisicing elit. Ab quo consequatur similique iste mollitia commodi architecto inventore recusandae officia, quas dicta? Ratione adipisci alias perferendis voluptas nesciunt ut amet unde.",
          "created_at": "1668990427",
          "updated_at": "1671582429",
          "label": [
            {
              "id": 1,
              "name": "label 1",
              "description": "Descrição da label 1",
              "created_at": "1668990427",
              "updated_at": "1671582429"
            },
            {
              "id": 2,
              "name": "label 2",
              "note_body": "Descrição da label 2",
              "created_at": "1668990427",
              "updated_at": "1671582429"
            }
          ]
        }
      ]
    },
    {
      "id": 2,
      "email": "username2@gmail.com",
      "created_at": "1668990427",
      "updated_at": "1671582429",
      "notes": [
        {
          "id": 2,
          "user_id": 2,
          "note_body": "Lorem ipsum dolor sit amet consectetur adipisicing elit. Ipsam eaque vitae maxime, consequatur aut aspernatur ducimus sequi quo aliquid id eum, omnis consectetur excepturi esse! Nam autem eum assumenda voluptatum?",
          "created_at": "1668990427",
          "updated_at": "1671582429",
          "label": [
            {
              "id": 1,
              "name": "label 1",
              "description": "Descrição da label 1",
              "created_at": "1668990427",
              "updated_at": "1671582429"
            },
            {
              "id": 2,
              "name": "label 2",
              "note_body": "Descrição da label 2",
              "created_at": "1668990427",
              "updated_at": "1671582429"
            }
          ]
        }
      ]
    }
  ]
}
